pyTigerDriver/__init__.py
pyTigerDriver/misc.py
pyTigerDriver/pyDriver.py
pyTigerDriver-1.0.14.dist-info/LICENSE
pyTigerDriver-1.0.14.dist-info/METADATA
pyTigerDriver-1.0.14.dist-info/WHEEL
pyTigerDriver-1.0.14.dist-info/top_level.txt
pyTigerDriver-1.0.14.dist-info/RECORD
