Metadata-Version: 2.1
Name: pyTigerDriver
Version: 1.0.14
Summary: GSQL client for TigerGraph
Home-page: https://github.com/Zrouga-Mohamed/pyTigerDriver 
Author: Zrouga Mohamed
Author-email: medzrouga@gmail.com
License: UNKNOWN
Keywords: gsql,client,tigergraph
Platform: UNKNOWN
Classifier: Development Status :: 5 - Production/Stable
Classifier: Programming Language :: Python :: 3
Classifier: License :: OSI Approved :: GNU Affero General Public License v3
Classifier: Operating System :: OS Independent
Classifier: Topic :: Database
Requires: requests
Requires-Python: >=3.5
